LICENSE
MANIFEST.in
NEWS
README.rst
setup.cfg
setup.py
docs/add_custom_css.py
docs/advanced.rst
docs/annotated-atom03.rst
docs/annotated-atom10.rst
docs/annotated-examples.rst
docs/annotated-rss10.rst
docs/annotated-rss20-dc.rst
docs/annotated-rss20.rst
docs/atom-detail.rst
docs/basic-existence.rst
docs/basic.rst
docs/bozo.rst
docs/changes-26.rst
docs/changes-27.rst
docs/changes-30.rst
docs/changes-301.rst
docs/changes-31.rst
docs/changes-32.rst
docs/changes-33.rst
docs/changes-40.rst
docs/changes-401.rst
docs/changes-402.rst
docs/changes-41.rst
docs/changes-42.rst
docs/changes-early.rst
docs/character-encoding.rst
docs/common-atom-elements.rst
docs/common-rss-elements.rst
docs/conf.py
docs/content-normalization.rst
docs/date-parsing.rst
docs/history.rst
docs/html-sanitization.rst
docs/http-authentication.rst
docs/http-etag.rst
docs/http-other.rst
docs/http-redirect.rst
docs/http-useragent.rst
docs/http.rst
docs/index.rst
docs/introduction.rst
docs/license.rst
docs/namespace-handling.rst
docs/reference-bozo.rst
docs/reference-bozo_exception.rst
docs/reference-encoding.rst
docs/reference-entry-author.rst
docs/reference-entry-author_detail.rst
docs/reference-entry-comments.rst
docs/reference-entry-content.rst
docs/reference-entry-contributors.rst
docs/reference-entry-created.rst
docs/reference-entry-created_parsed.rst
docs/reference-entry-enclosures.rst
docs/reference-entry-expired.rst
docs/reference-entry-expired_parsed.rst
docs/reference-entry-id.rst
docs/reference-entry-license.rst
docs/reference-entry-link.rst
docs/reference-entry-links.rst
docs/reference-entry-published.rst
docs/reference-entry-published_parsed.rst
docs/reference-entry-publisher.rst
docs/reference-entry-publisher_detail.rst
docs/reference-entry-source.rst
docs/reference-entry-summary.rst
docs/reference-entry-summary_detail.rst
docs/reference-entry-tags.rst
docs/reference-entry-title.rst
docs/reference-entry-title_detail.rst
docs/reference-entry-updated.rst
docs/reference-entry-updated_parsed.rst
feedparser_homeassistant.egg-info/PKG-INFO
feedparser_homeassistant.egg-info/SOURCES.txt
feedparser_homeassistant.egg-info/dependency_links.txt
feedparser_homeassistant.egg-info/requires.txt
feedparser_homeassistant.egg-info/top_level.txt
